[{"id":1,"first_name":"Hugh","last_name":"Irdale","adress":"16 Crowley Terrace","email":"hirdale0@bing.com","phone":"+54-940-769-3072"},
{"id":2,"first_name":"Dinah","last_name":"Achurch","adress":"362 Green Hill","email":"dachurch1@cloudflare.com","phone":"+86-340-459-9722"},
{"id":3,"first_name":"Gradeigh","last_name":"Frean","adress":"4933 Northview Crossing","email":"gfrean2@ow.ly","phone":"+380-949-373-9126"},
{"id":4,"first_name":"Ben","last_name":"Bromilow","adress":"87382 Iowa Center","email":"bbromilow3@patch.com","phone":"+51-640-754-9744"},
{"id":5,"first_name":"Kelly","last_name":"Hainsworth","adress":"58 Eastwood Road","email":"khainsworth4@gizmodo.com","phone":"+355-756-155-7586"},
{"id":6,"first_name":"Webb","last_name":"Frend","adress":"710 High Crossing Place","email":"wfrend5@hp.com","phone":"+86-861-989-5892"},
{"id":7,"first_name":"Trixi","last_name":"Ary","adress":"53247 Dryden Plaza","email":"tary6@exblog.jp","phone":"+962-943-855-8809"},
{"id":8,"first_name":"Lil","last_name":"Hackleton","adress":"3 Schmedeman Way","email":"lhackleton7@nymag.com","phone":"+62-269-299-7168"},
{"id":9,"first_name":"Doralyn","last_name":"Gurg","adress":"986 Sherman Lane","email":"dgurg8@washingtonpost.com","phone":"+351-225-689-7371"},
{"id":10,"first_name":"Vernor","last_name":"Gircke","adress":"384 Luster Court","email":"vgircke9@nytimes.com","phone":"+420-600-562-6620"},
{"id":11,"first_name":"Carena","last_name":"Bealton","adress":"6501 Packers Road","email":"cbealtona@ameblo.jp","phone":"+7-819-710-1444"},
{"id":12,"first_name":"Leann","last_name":"Bisterfeld","adress":"4405 Riverside Center","email":"lbisterfeldb@bluehost.com","phone":"+57-283-644-6935"},
{"id":13,"first_name":"Vernen","last_name":"Titchmarsh","adress":"55381 Eastlawn Point","email":"vtitchmarshc@aboutads.info","phone":"+86-153-429-4936"},
{"id":14,"first_name":"Kippy","last_name":"Tedman","adress":"90439 Schiller Circle","email":"ktedmand@loc.gov","phone":"+351-946-993-1792"},
{"id":15,"first_name":"Hart","last_name":"Conningham","adress":"581 Moland Circle","email":"hconninghame@vkontakte.ru","phone":"+351-427-630-8160"},
{"id":16,"first_name":"Othello","last_name":"Samwaye","adress":"1 Lighthouse Bay Center","email":"osamwayef@squidoo.com","phone":"+58-944-587-9455"},
{"id":17,"first_name":"Karil","last_name":"Ambrogioni","adress":"42173 Myrtle Crossing","email":"kambrogionig@amazon.de","phone":"+351-844-995-4979"},
{"id":18,"first_name":"Raoul","last_name":"Le Barr","adress":"8 Sauthoff Hill","email":"rlebarrh@nationalgeographic.com","phone":"+52-925-913-6712"},
{"id":19,"first_name":"Miguelita","last_name":"Twaits","adress":"7000 Golf View Circle","email":"mtwaitsi@answers.com","phone":"+351-996-501-6028"},
{"id":20,"first_name":"Wendie","last_name":"Goodsir","adress":"2262 Forest Crossing","email":"wgoodsirj@umich.edu","phone":"+1-323-615-8003"},
{"id":21,"first_name":"Armando","last_name":"Hogben","adress":"19039 Old Gate Avenue","email":"ahogbenk@amazon.co.uk","phone":"+62-550-283-6264"},
{"id":22,"first_name":"Belva","last_name":"Vallance","adress":"831 Johnson Crossing","email":"bvallancel@typepad.com","phone":"+52-292-728-5620"},
{"id":23,"first_name":"Thekla","last_name":"Cirlos","adress":"272 Clove Hill","email":"tcirlosm@sitemeter.com","phone":"+33-755-839-8851"},
{"id":24,"first_name":"Linnie","last_name":"Gumary","adress":"424 Vahlen Crossing","email":"lgumaryn@about.me","phone":"+86-932-344-1883"},
{"id":25,"first_name":"Lanita","last_name":"Klewi","adress":"93 Debra Street","email":"lklewio@cbslocal.com","phone":"+52-675-656-4849"},
{"id":26,"first_name":"Gay","last_name":"Stobo","adress":"589 Linden Circle","email":"gstobop@reuters.com","phone":"+1-713-504-5211"},
{"id":27,"first_name":"Malinda","last_name":"Maryott","adress":"2 Barby Crossing","email":"mmaryottq@dot.gov","phone":"+7-709-869-6495"},
{"id":28,"first_name":"Joscelin","last_name":"Waleworke","adress":"7 Melby Junction","email":"jwaleworker@theguardian.com","phone":"+45-961-732-8064"},
{"id":29,"first_name":"Boniface","last_name":"Kienlein","adress":"3 Old Shore Drive","email":"bkienleins@reverbnation.com","phone":"+48-311-630-2364"},
{"id":30,"first_name":"Ethelind","last_name":"Schruur","adress":"04 Alpine Plaza","email":"eschruurt@exblog.jp","phone":"+66-810-674-5693"}]